Metadata-Version: 1.0
Name: ti83f
Version: 0.2.1
Summary: Encode and decode TI83F files
Home-page: UNKNOWN
Author: Koen van Vliet
Author-email: 8by8mail@gmail.com
License: MIT
Platform: UNKNOWN
